pep263/__init__.py
pep263/cli.py
pep263/core.py
pep263/decorators.py
pep263/errors.py
pep263-1.0.0.dist-info/METADATA
pep263-1.0.0.dist-info/RECORD
pep263-1.0.0.dist-info/WHEEL
pep263-1.0.0.dist-info/entry_points.txt
pep263-1.0.0.dist-info/top_level.txt
